[{"id":"fact-map--URnZAYqR","date":"2018-05-21T12:30:17.440Z","mediaFilename":"fact-map--URnZAYqR.png","altText":"instances of Limited Company map","caption":"Favorite instances of Limited Company by state","postedToGit":true,"htmlFragment":"<li class=\"pane\">\n  <div class=\"time-stamp entry-meta\">\n    <a href=\"fact-map--URnZAYqR.html\">\n      <time datetime=\"2018-05-21T12:30:17.440Z\">2018-5-21 08:30:17</time>\n    </a>\n  </div><img src=\"media/fact-map--URnZAYqR.png\" alt=\"instances of Limited Company map\"></video><div class=\"media-caption entry-meta\">Favorite instances of Limited Company by state</div></li>","postedSingleVideoPage":true},{"id":"fact-map--uQXlwVzM","date":"2018-05-21T15:30:16.962Z","mediaFilename":"fact-map--uQXlwVzM.png","altText":"things used for Boarding Bus map","caption":"Which things used for Boarding Bus does your state hate the most?","postedToGit":true,"htmlFragment":"<li class=\"pane\">\n  <div class=\"time-stamp entry-meta\">\n    <a href=\"fact-map--uQXlwVzM.html\">\n      <time datetime=\"2018-05-21T15:30:16.962Z\">2018-5-21 11:30:16</time>\n    </a>\n  </div><img src=\"media/fact-map--uQXlwVzM.png\" alt=\"things used for Boarding Bus map\"></video><div class=\"media-caption entry-meta\">Which things used for Boarding Bus does your state hate the most?</div></li>","postedSingleVideoPage":true},{"id":"fact-map--AnoGUXXY","date":"2018-05-21T18:30:17.173Z","mediaFilename":"fact-map--AnoGUXXY.png","altText":"uses of Having Checkup map","caption":"Which uses of Having Checkup does your state love the most?","postedToGit":true,"htmlFragment":"<li class=\"pane\">\n  <div class=\"time-stamp entry-meta\">\n    <a href=\"fact-map--AnoGUXXY.html\">\n      <time datetime=\"2018-05-21T18:30:17.173Z\">2018-5-21 14:30:17</time>\n    </a>\n  </div><img src=\"media/fact-map--AnoGUXXY.png\" alt=\"uses of Having Checkup map\"></video><div class=\"media-caption entry-meta\">Which uses of Having Checkup does your state love the most?</div></li>","postedSingleVideoPage":true},{"id":"fact-map--qosoGCTP","date":"2018-05-21T21:30:17.836Z","mediaFilename":"fact-map--qosoGCTP.png","altText":"Taxa named by Étienne Mulsant map","caption":"Favorite Taxa named by Étienne Mulsant by state","postedToGit":true,"htmlFragment":"<li class=\"pane\">\n  <div class=\"time-stamp entry-meta\">\n    <a href=\"fact-map--qosoGCTP.html\">\n      <time datetime=\"2018-05-21T21:30:17.836Z\">2018-5-21 17:30:17</time>\n    </a>\n  </div><img src=\"media/fact-map--qosoGCTP.png\" alt=\"Taxa named by Étienne Mulsant map\"></video><div class=\"media-caption entry-meta\">Favorite Taxa named by Étienne Mulsant by state</div></li>","postedSingleVideoPage":true},{"id":"fact-map--UfaydnuG","date":"2018-05-22T00:30:17.562Z","mediaFilename":"fact-map--UfaydnuG.png","altText":"Sportspeople from Newcastle-under-Lyme map","caption":"Favorite Sportspeople from Newcastle-under-Lyme by state","postedToGit":true,"htmlFragment":"<li class=\"pane\">\n  <div class=\"time-stamp entry-meta\">\n    <a href=\"fact-map--UfaydnuG.html\">\n      <time datetime=\"2018-05-22T00:30:17.562Z\">2018-5-21 20:30:17</time>\n    </a>\n  </div><img src=\"media/fact-map--UfaydnuG.png\" alt=\"Sportspeople from Newcastle-under-Lyme map\"></video><div class=\"media-caption entry-meta\">Favorite Sportspeople from Newcastle-under-Lyme by state</div></li>","postedSingleVideoPage":true},{"id":"fact-map--zuhncKEu","date":"2018-05-22T03:30:17.690Z","mediaFilename":"fact-map--zuhncKEu.png","altText":"locations of Control Room map","caption":"Favorite locations of Control Room by state","postedToGit":true,"htmlFragment":"<li class=\"pane\">\n  <div class=\"time-stamp entry-meta\">\n    <a href=\"fact-map--zuhncKEu.html\">\n      <time datetime=\"2018-05-22T03:30:17.690Z\">2018-5-21 23:30:17</time>\n    </a>\n  </div><img src=\"media/fact-map--zuhncKEu.png\" alt=\"locations of Control Room map\"></video><div class=\"media-caption entry-meta\">Favorite locations of Control Room by state</div></li>","postedSingleVideoPage":true},{"id":"fact-map--upZTrnfy","date":"2018-05-22T06:30:17.047Z","mediaFilename":"fact-map--upZTrnfy.png","altText":"things used for Beat Up map","caption":"Which things used for Beat Up does your state love the most?","postedToGit":true,"htmlFragment":"<li class=\"pane\">\n  <div class=\"time-stamp entry-meta\">\n    <a href=\"fact-map--upZTrnfy.html\">\n      <time datetime=\"2018-05-22T06:30:17.047Z\">2018-5-22 02:30:17</time>\n    </a>\n  </div><img src=\"media/fact-map--upZTrnfy.png\" alt=\"things used for Beat Up map\"></video><div class=\"media-caption entry-meta\">Which things used for Beat Up does your state love the most?</div></li>","postedSingleVideoPage":true}]