[{"id":"fact-map--gKQvASDd","date":"2018-06-14T03:30:17.759Z","mediaFilename":"fact-map--gKQvASDd.png","altText":"things Hard Work makes you want map","caption":"Favorite things Hard Work makes you want by state","postedToGit":true,"htmlFragment":"<li class=\"pane\">\n  <div class=\"time-stamp entry-meta\">\n    <a href=\"fact-map--gKQvASDd.html\">\n      <time datetime=\"2018-06-14T03:30:17.759Z\">2018-6-13 23:30:17</time>\n    </a>\n  </div><img src=\"media/fact-map--gKQvASDd.png\" alt=\"things Hard Work makes you want map\"></video><div class=\"media-caption entry-meta\">Favorite things Hard Work makes you want by state</div></li>","postedSingleVideoPage":true},{"id":"fact-map--tInivLUw","date":"2018-06-14T06:30:17.689Z","mediaFilename":"fact-map--tInivLUw.png","altText":"steps of Going to Opera map","caption":"Favorite steps of Going to Opera by state","postedToGit":true,"htmlFragment":"<li class=\"pane\">\n  <div class=\"time-stamp entry-meta\">\n    <a href=\"fact-map--tInivLUw.html\">\n      <time datetime=\"2018-06-14T06:30:17.689Z\">2018-6-14 02:30:17</time>\n    </a>\n  </div><img src=\"media/fact-map--tInivLUw.png\" alt=\"steps of Going to Opera map\"></video><div class=\"media-caption entry-meta\">Favorite steps of Going to Opera by state</div></li>","postedSingleVideoPage":true},{"id":"fact-map--NFnuGskp","date":"2018-06-14T09:30:18.512Z","mediaFilename":"fact-map--NFnuGskp.png","altText":"religions map","caption":"What do the states think of religions?","postedToGit":true,"htmlFragment":"<li class=\"pane\">\n  <div class=\"time-stamp entry-meta\">\n    <a href=\"fact-map--NFnuGskp.html\">\n      <time datetime=\"2018-06-14T09:30:18.512Z\">2018-6-14 05:30:18</time>\n    </a>\n  </div><img src=\"media/fact-map--NFnuGskp.png\" alt=\"religions map\"></video><div class=\"media-caption entry-meta\">What do the states think of religions?</div></li>","postedSingleVideoPage":true}]